swift_apple/__init__.py
swift_apple/random.py
swift_apple/swift.py
swift_module_elseTests-1.1.7.dist-info/LICENSE.txt
swift_module_elseTests-1.1.7.dist-info/METADATA
swift_module_elseTests-1.1.7.dist-info/WHEEL
swift_module_elseTests-1.1.7.dist-info/top_level.txt
swift_module_elseTests-1.1.7.dist-info/RECORD
