Metadata-Version: 2.1
Name: swift-module-elseTests
Version: 1.1.7
Summary: add some new project,you can use "pip install swift-module-elseTests" command get it.
Home-page: https://github.com/pypa/sampleproject
Author: Expert Author
Author-email: Wf6350177@163.com
License: UNKNOWN
Project-URL: Bug Tracker, https://github.com/monkeyhammercopiseded/swift_apple-swift-module-elseTests-/issues
Platform: UNKNOWN
Classifier: Programming Language :: Python :: 3
Classifier: License :: OSI Approved :: MIT License
Classifier: Operating System :: OS Independent
Requires-Python: >=2.7
License-File: LICENSE.txt
